config/__init__.py
config/gui_data.py
eClinic-1.0.dist-info/DESCRIPTION.rst
eClinic-1.0.dist-info/METADATA
eClinic-1.0.dist-info/RECORD
eClinic-1.0.dist-info/WHEEL
eClinic-1.0.dist-info/metadata.json
eClinic-1.0.dist-info/top_level.txt
gui/__init__.py
gui/config_data.py
gui/labrequest.py
gui/labresults.py
gui/pharmacy.py
gui/search.py
gui/vitals.py
gui/admin/__init__.py
gui/admin/drugs.py
gui/admin/procedures.py
gui/admin/usables.py
gui/admin/users.py
my_widgets/Normal_Ranges.py
my_widgets/__init__.py
my_widgets/cbc.py
my_widgets/datefield.py
my_widgets/doseconverter.py
my_widgets/features.py
my_widgets/general.py
my_widgets/menuframework.py
my_widgets/numbers.py
my_widgets/py2html.py
my_widgets/table.py
my_widgets/tooltip.py
my_widgets/tree.py
my_widgets/widgets.py
my_widgets/word_docx.py
spreadsheets/__init__.py
spreadsheets/prescription_sheet.py
spreadsheets/procedures_sheet.py
spreadsheets/receipt.py
spreadsheets/usables_sheet.py
