Metadata-Version: 2.0
Name: eClinic
Version: 1.0
Summary: A LAN based electronic clinical management system
Home-page: https://github.com/abiiranathan/eclinic
Author: Dr Abiira Nathan
Author-email: nabiira2by2@gmail.com
License: GPL-3
Keywords: eclinic Electronic Medical Database
Platform: Windows 7
Platform: Windows 8
Platform: Windows 10
Requires-Dist: PIL
Requires-Dist: Pmw
Requires-Dist: ast
Requires-Dist: lxml
Requires-Dist: mysql-connector-python
Requires-Dist: pyautogui
Requires-Dist: python-docx
